esigmapy/__init__.py
esigmapy/blend.py
esigmapy/generator.py
esigmapy/legacy.py
esigmapy/utils.py
esigmapy-2025.3.7.dist-info/LICENSE
esigmapy-2025.3.7.dist-info/METADATA
esigmapy-2025.3.7.dist-info/WHEEL
esigmapy-2025.3.7.dist-info/top_level.txt
esigmapy-2025.3.7.dist-info/RECORD
